mypubsub/__init__.py
mypubsub/__main__.py
mypubsub/modules/__init__.py
mypubsub/modules/singleton/__init__.py
mypubsub/modules/singleton/singleton_base.py
MyPubSub-0.1.1.dist-info/METADATA
MyPubSub-0.1.1.dist-info/WHEEL
MyPubSub-0.1.1.dist-info/top_level.txt
MyPubSub-0.1.1.dist-info/RECORD
